<?xml version="1.0"?>

<!DOCTYPE weblogic-ejb-jar PUBLIC "-//BEA Systems, Inc.//DTD WebLogic 6.0.0 EJB//EN" "http://www.bea.com/servers/wls600/dtd/weblogic-ejb-jar.dtd" >

<weblogic-ejb-jar>

    <weblogic-enterprise-bean>
      <ejb-name>AuthorizationSession</ejb-name>
      <transaction-descriptor>
        <trans-timeout-seconds>900</trans-timeout-seconds>
      </transaction-descriptor>
      <jndi-name>AuthorizationSession</jndi-name>
    </weblogic-enterprise-bean>

    <weblogic-enterprise-bean>
      <ejb-name>AdminGroupData</ejb-name>
      <entity-descriptor>
        <persistence>
          <persistence-type>
            <type-identifier>WebLogic_CMP_RDBMS</type-identifier>
            <type-version>7.0</type-version>
            <type-storage>META-INF/weblogic-cmp-rdbms-jar.xml</type-storage>
          </persistence-type>
          <persistence-use>
            <type-identifier>WebLogic_CMP_RDBMS</type-identifier>
            <type-version>7.0</type-version>
          </persistence-use>
        </persistence>
      </entity-descriptor>
      <jndi-name>AdminGroupData</jndi-name>
    </weblogic-enterprise-bean>

    <weblogic-enterprise-bean>
      <ejb-name>AdminEntityData</ejb-name>
      <entity-descriptor>
        <persistence>
          <persistence-type>
            <type-identifier>WebLogic_CMP_RDBMS</type-identifier>
            <type-version>7.0</type-version>
            <type-storage>META-INF/weblogic-cmp-rdbms-jar.xml</type-storage>
          </persistence-type>
          <persistence-use>
            <type-identifier>WebLogic_CMP_RDBMS</type-identifier>
            <type-version>7.0</type-version>
          </persistence-use>
        </persistence>
      </entity-descriptor>
      <jndi-name>AdminEntityData</jndi-name>
    </weblogic-enterprise-bean>

    <weblogic-enterprise-bean>
      <ejb-name>AccessRulesData</ejb-name>
      <entity-descriptor>
        <persistence>
          <persistence-type>
            <type-identifier>WebLogic_CMP_RDBMS</type-identifier>
            <type-version>7.0</type-version>
            <type-storage>META-INF/weblogic-cmp-rdbms-jar.xml</type-storage>
          </persistence-type>
          <persistence-use>
            <type-identifier>WebLogic_CMP_RDBMS</type-identifier>
            <type-version>7.0</type-version>
          </persistence-use>
        </persistence>
      </entity-descriptor>
      <jndi-name>AccessRulesData</jndi-name>
    </weblogic-enterprise-bean>


    <weblogic-enterprise-bean>
      <ejb-name>AuthorizationTreeUpdateData</ejb-name>
      <entity-descriptor>
        <persistence>
          <persistence-type>
            <type-identifier>WebLogic_CMP_RDBMS</type-identifier>
            <type-version>7.0</type-version>
            <type-storage>META-INF/weblogic-cmp-rdbms-jar.xml</type-storage>
          </persistence-type>
          <persistence-use>
            <type-identifier>WebLogic_CMP_RDBMS</type-identifier>
            <type-version>7.0</type-version>
          </persistence-use>
        </persistence>
      </entity-descriptor>
      <jndi-name>AuthorizationTreeUpdateData</jndi-name>
    </weblogic-enterprise-bean>




   <security-role-assignment>
      <role-name>InternalUser</role-name>
      <principal-name>system</principal-name>
   </security-role-assignment>
   <security-role-assignment>
      <role-name>SuperAdmin</role-name>
      <principal-name>CH</principal-name>
   </security-role-assignment>
   <security-role-assignment>
      <role-name>everyone</role-name>
      <principal-name>everyone</principal-name>
   </security-role-assignment>

</weblogic-ejb-jar>
